.gitignore
LICENSE.txt
Makefile
README.md
requirements.txt
setup.py
sonar-project.properties
django_pypiwik/__init__.py
django_pypiwik/admin.py
django_pypiwik/decorators.py
django_pypiwik/middleware.py
django_pypiwik/models.py
django_pypiwik/tracker.py
django_pypiwik/views.py
django_pypiwik.egg-info/PKG-INFO
django_pypiwik.egg-info/SOURCES.txt
django_pypiwik.egg-info/dependency_links.txt
django_pypiwik.egg-info/not-zip-safe
django_pypiwik.egg-info/top_level.txt
django_pypiwik/migrations/0001_initial.py
django_pypiwik/migrations/0002_auto_20150718_1439.py
django_pypiwik/migrations/0003_auto_20151101_0657.py
django_pypiwik/migrations/__init__.py