Metadata-Version: 1.1
Name: django-pypiwik
Version: 0.1.9
Summary: Django helper application around pypiwik
Home-page: https://ercpe.de/projects/django-pypiwik
Author: Johann Schmitz
Author-email: johann@j-schmitz.net
License: GPL-3
Download-URL: https://code.not-your-server.de/django-pypiwik.git/tags/
Platform: UNKNOWN
